discord_save/__init__.py
discord_save/save_manager.py
discord_save-0.1.0.dist-info/LICENSE
discord_save-0.1.0.dist-info/METADATA
discord_save-0.1.0.dist-info/WHEEL
discord_save-0.1.0.dist-info/top_level.txt
discord_save-0.1.0.dist-info/RECORD
