Metadata-Version: 2.1
Name: discord-save
Version: 0.1.0
Summary: A library for managing save files for Discord bots.
Home-page: https://github.com/yourusername/discord_save
Author: Your Name
Author-email: your.email@example.com
Classifier: Programming Language :: Python :: 3
Classifier: License :: OSI Approved :: MIT License
Requires-Python: >=3.6
License-File: LICENSE
